agentharnessengine-0.7.0.dist-info/licenses/LICENSE
governance/__init__.py
governance/adapters.py
governance/agent.py
governance/audit.py
governance/behavior.py
governance/constraints.py
governance/coordination.py
governance/enforcement.py
governance/escalation.py
governance/evaluation.py
governance/extractor.py
governance/failures.py
governance/guarantees.py
governance/guardrails.py
governance/interface.py
governance/kernel.py
governance/mechanics.py
governance/metrics.py
governance/modes.py
governance/observation.py
governance/policy.py
governance/policy_engine.py
governance/profiles.py
governance/result.py
governance/signals.py
governance/state.py
governance/validator.py
governance/temporal/__init__.py
governance/temporal/controls.py
governance/temporal/signals.py
agentharnessengine-0.7.0.dist-info/METADATA
agentharnessengine-0.7.0.dist-info/WHEEL
agentharnessengine-0.7.0.dist-info/top_level.txt
agentharnessengine-0.7.0.dist-info/RECORD
