Metadata-Version: 2.4
Name: agentharnessengine
Version: 0.7.0
Summary: A runtime governance layer that enforces hard behavioral bounds in autonomous agents.
Author: Sarthaksahu777
License: MIT
Project-URL: Homepage, https://github.com/Sarthaksahu777/Emocore
Project-URL: Repository, https://github.com/Sarthaksahu777/Emocore
Project-URL: Documentation, https://github.com/Sarthaksahu777/Emocore#readme
Keywords: agents,runtime,governance,control,AI,LLM,safety
Classifier: Development Status :: 4 - Beta
Classifier: Intended Audience :: Developers
Classifier: Intended Audience :: Science/Research
Classifier: Programming Language :: Python :: 3
Classifier: Programming Language :: Python :: 3.10
Classifier: Programming Language :: Python :: 3.11
Classifier: Programming Language :: Python :: 3.12
Classifier: Programming Language :: Python :: 3.13
Classifier: Programming Language :: Python :: 3 :: Only
Classifier: License :: OSI Approved :: MIT License
Classifier: Operating System :: OS Independent
Classifier: Topic :: Scientific/Engineering :: Artificial Intelligence
Requires-Python: >=3.10
License-File: LICENSE
Requires-Dist: numpy
Provides-Extra: dev
Requires-Dist: pytest>=7.0; extra == "dev"
Requires-Dist: pytest-cov; extra == "dev"
Provides-Extra: examples
Requires-Dist: autogen; extra == "examples"
Requires-Dist: crewai; extra == "examples"
Requires-Dist: langchain; extra == "examples"
Requires-Dist: langchain-openai; extra == "examples"
Requires-Dist: openai; extra == "examples"
Dynamic: license-file
